secure_fountain/__init__.py
secure_fountain/main.py
secure_fountain-0.0.1a0.dist-info/LICENSE
secure_fountain-0.0.1a0.dist-info/LICENSE.md
secure_fountain-0.0.1a0.dist-info/METADATA
secure_fountain-0.0.1a0.dist-info/WHEEL
secure_fountain-0.0.1a0.dist-info/top_level.txt
secure_fountain-0.0.1a0.dist-info/RECORD
