Metadata-Version: 2.1
Name: secure-fountain
Version: 0.0.1a0
Summary: Prototype implementation of the secure fountain architecture
Home-page: https://github.com/geometry-labs/secure-fountain
Author: Geometry Labs
Author-email: info@geometrylabs.io
License: MIT
Keywords: secure fountain,secure fountain architecture,storage,scaling
Classifier: Development Status :: 5 - Production/Stable
Classifier: Environment :: Console
Classifier: Intended Audience :: Developers
Classifier: Intended Audience :: Science/Research
Classifier: Intended Audience :: Financial and Insurance Industry
Classifier: Natural Language :: English
Classifier: License :: OSI Approved :: MIT License
Classifier: Programming Language :: Python :: 3 :: Only
Classifier: Programming Language :: Python :: 3
Classifier: Programming Language :: Python :: 3.6
Classifier: Programming Language :: Python :: 3.7
Classifier: Programming Language :: Python :: 3.8
Classifier: Programming Language :: Python :: 3.9
Classifier: Programming Language :: Python :: 3.10
Classifier: Programming Language :: Python :: Implementation :: CPython
Classifier: Programming Language :: Python :: Implementation :: PyPy
Classifier: Programming Language :: Python
Classifier: Topic :: Software Development
Classifier: Topic :: Scientific/Engineering :: Mathematics
Classifier: Topic :: Security :: Cryptography
Classifier: Typing :: Typed
Requires-Python: >=3.6
License-File: LICENSE
License-File: LICENSE.md
